ron/__init__.py
ron/mapper.py
ron/models.py
ron/parser.py
ron/py.typed
ron/visitor.py
ron/_generated/Ron.interp
ron/_generated/Ron.tokens
ron/_generated/RonLexer.interp
ron/_generated/RonLexer.py
ron/_generated/RonLexer.tokens
ron/_generated/RonParser.py
ron/_generated/RonVisitor.py
ron/_generated/__init__.py
ron_python-0.0.2.dist-info/METADATA
ron_python-0.0.2.dist-info/WHEEL
ron_python-0.0.2.dist-info/licenses/LICENSE
ron_python-0.0.2.dist-info/RECORD
