Metadata-Version: 2.4
Name: ron-python
Version: 0.0.2
Summary: Python reader for Rusty Object Notation
Project-URL: Documentation, https://juliancoffee.github.io/ron-py/latest/
Project-URL: Repository, https://github.com/juliancoffee/ron-py.git
Project-URL: Issues, https://github.com/juliancoffee/ron-py/issues
Project-URL: Releases, https://github.com/juliancoffee/ron-py/releases
License-File: LICENSE
Requires-Python: >=3.12
Requires-Dist: antlr4-python3-runtime>=4.13.2
Requires-Dist: frozendict>=2.4.7
